setup.py
gbjl_probability/Binomialdistribution.py
gbjl_probability/Gaussiandistribution.py
gbjl_probability/Generaldistribution.py
gbjl_probability/__init__.py
gbjl_probability.egg-info/PKG-INFO
gbjl_probability.egg-info/SOURCES.txt
gbjl_probability.egg-info/dependency_links.txt
gbjl_probability.egg-info/not-zip-safe
gbjl_probability.egg-info/top_level.txt