Metadata-Version: 1.0
Name: gbjl-probability
Version: 1.2
Summary: Analyze Gaussian and Binomial distributions
Home-page: UNKNOWN
Author: Jorge Nustes
Author-email: jlnustes@gmail.com
License: UNKNOWN
Platform: UNKNOWN
